examples/__init__.py
i75/__init__.py
i75/basei75.py
i75/colour.py
i75/datetime.py
i75/emulatedi75.py
i75/graphics.py
i75/image.py
i75/nativei75.py
i75/py.typed
i75/text.py
i75/emulated/hub75.py
i75/emulated/machine.py
i75/emulated/micropython.py
i75/emulated/mp_time.py
i75/emulated/network.py
i75/emulated/ntptime.py
i75/emulated/pen.py
i75/emulated/picographics.py
i75/emulated/pimoroni.py
i75/emulated/pimoroni_i2c.py
i75/emulated/urequests.py
i75/fontdata/cg_pixel_3x5_5.py
i75/stubs/gc.pyi
i75/stubs/machine.pyi
i75/stubs/time.pyi
i75/tz/__init__.py
i75/tz/europe_london.py
i75-1.17.0.data/scripts/i75
i75-1.17.0.data/scripts/i75-convert-image
tests/__init__.py
tests/test_datetime.py
tests/test_emulatedi75.py
tests/test_image.py
tests/test_linedrawing.py
tests/test_text.py
tests/emulated/__init__.py
tests/emulated/test_machine.py
tests/emulated/test_pen.py
tests/emulated/test_picographics.py
tests/tz/__init__.py
tests/tz/test_europe_london.py
i75-1.17.0.dist-info/LICENSE
i75-1.17.0.dist-info/METADATA
i75-1.17.0.dist-info/WHEEL
i75-1.17.0.dist-info/top_level.txt
i75-1.17.0.dist-info/RECORD
