Metadata-Version: 2.1
Name: i75
Version: 1.17.0
Summary: A wrapper around Pimoroni's `interstate75` library which allows for running locally and easier testing.
Home-page: https://github.com/andrewjw/i75
Author: Andrew Wilkinson
Author-email: andrewjwilkinson@gmail.com
Classifier: Programming Language :: Python :: 3.8
Classifier: Programming Language :: Python :: 3.9
Classifier: Programming Language :: Python :: 3.10
Classifier: Programming Language :: Python :: 3.11
Classifier: Programming Language :: Python :: 3.12
Classifier: License :: OSI Approved :: GNU General Public License v3 (GPLv3)
Classifier: Operating System :: OS Independent
Requires-Python: >=3.8
License-File: LICENSE
Requires-Dist: pycodestyle==2.12.1
Requires-Dist: coveralls==4.0.1
Requires-Dist: pygame==2.6.1
Requires-Dist: python-semantic-release==9.15.1
Requires-Dist: mypy==1.13.0
Requires-Dist: wheel==0.45.1
Requires-Dist: micropython-rp2-pico-stubs==1.20.0.post5
Requires-Dist: adafruit-ampy==1.1.0
Requires-Dist: twine==5.1.1
Requires-Dist: requests==2.32.3
Requires-Dist: types-requests==2.32.0.20241016
Requires-Dist: Pillow==10.4.0
Requires-Dist: types-Pillow==10.2.0.20240822
